polecat_auth/__init__.py
polecat_auth/admin.py
polecat_auth/app.py
polecat_auth/exceptions.py
polecat_auth/migrations/0001_migration.py
polecat_auth/migrations/__init__.py
polecat_auth/models.py
polecat_auth/mutations.py
polecat_auth/policies.py
polecat_auth/resolvers.py
polecat_auth/roles.py
polecat_auth/services.py
polecat_auth-0.0.1.dist-info/WHEEL
polecat_auth-0.0.1.dist-info/METADATA
polecat_auth-0.0.1.dist-info/RECORD
