Metadata-Version: 2.1
Name: polecat-auth
Version: 0.0.1
Summary: 
Author: Luke Hodkinson
Author-email: furious.luke@gmail.com
Requires-Python: >=3.7,<4.0
Classifier: Programming Language :: Python :: 3
Classifier: Programming Language :: Python :: 3.7
Classifier: Programming Language :: Python :: 3.8
Requires-Dist: polecat
